pymacies_arg/__init__.py
pymacies_arg/constants.py
pymacies_arg/core.py
pymacies_arg/extractor.py
pymacies_arg/loaders.py
pymacies_arg/transform.py
PymaciesArg-0.0.1.dist-info/LICENSE
PymaciesArg-0.0.1.dist-info/METADATA
PymaciesArg-0.0.1.dist-info/WHEEL
PymaciesArg-0.0.1.dist-info/top_level.txt
PymaciesArg-0.0.1.dist-info/RECORD
