Metadata-Version: 2.1
Name: PymaciesArg
Version: 0.0.1
Summary: An extension that registers all pharmacies in Argentina.
Home-page: https://github.com/juniors90/PymaciesArg
Author: Ferreira Juan David
Author-email: juandavid9a0@gmail.com
License: The MIT License
Project-URL: Source, https://github.com/juniors90/PymaciesArg
Project-URL: Tracker, https://github.com/juniors90/PymaciesArg/issues
Project-URL: Donate, https://www.paypal.com/donate?hosted_button_id=LFAQ7E7TJ4HSY
Project-URL: Funding, https://paypal.me/juniors90
Keywords: Pharmacies,Argentina,Data Science
Platform: any
Classifier: Development Status :: 4 - Beta
Classifier: License :: OSI Approved :: MIT License
Classifier: Operating System :: OS Independent
Classifier: Programming Language :: Python
Classifier: Programming Language :: Python :: 3.8
Classifier: Topic :: Internet :: WWW/HTTP :: Dynamic Content
Classifier: Topic :: Software Development :: Libraries :: Python Modules
License-File: LICENSE
Requires-Dist: pandas (==1.5.0)
Requires-Dist: requests (==2.28.1)
